op_cellar/__init__.py
op_cellar/download.py
op_cellar/parsers/__init__.py
op_cellar/parsers/akomantoso.py
op_cellar/parsers/formex.py
op_cellar/parsers/html.py
op_cellar/parsers/parser.py
op_cellar/sparql.py
op_cellar-0.0.3.dist-info/LICENSE
op_cellar-0.0.3.dist-info/METADATA
op_cellar-0.0.3.dist-info/WHEEL
op_cellar-0.0.3.dist-info/RECORD
