Metadata-Version: 2.1
Name: op_cellar
Version: 0.0.3
Summary: A generic package to query and retrieve documents from Cellar, the common data repository of the Publications Office of the European Union.
License: EUPL 1.2
Author: AlessioNar
Author-email: alessio.nardin@gmail.com
Requires-Python: >=3.11,<4.0
Classifier: License :: Other/Proprietary License
Classifier: Operating System :: OS Independent
Classifier: Programming Language :: Python :: 3
Classifier: Programming Language :: Python :: 3.11
Classifier: Programming Language :: Python :: 3.12
Classifier: Programming Language :: Python :: 3.13
Requires-Dist: beautifulsoup4 (>=4.12.3,<5.0.0)
Requires-Dist: chardet (>=5.2.0,<6.0.0)
Requires-Dist: lxml (>=5.3.0,<6.0.0)
Requires-Dist: pandas (>=2.2.3,<3.0.0)
Requires-Dist: pytest (>=8.3.3,<9.0.0)
Requires-Dist: requests (>=2.32.3,<3.0.0)
Requires-Dist: spacy (>=3.7.6,<4.0.0)
Requires-Dist: sparqlwrapper (>=2.0.0,<3.0.0)
